brief_develop/__init__.py
brief_develop/module.py
brief_develop-1.0.0.dist-info/licenses/LICENSE
brief_develop-1.0.0.dist-info/METADATA
brief_develop-1.0.0.dist-info/WHEEL
brief_develop-1.0.0.dist-info/top_level.txt
brief_develop-1.0.0.dist-info/RECORD
