Metadata-Version: 2.4
Name: brief-develop
Version: 1.0.0
Summary: 一个轻量级的Python测试框架，提供简洁的测试运行和彩色输出功能。
Author-email: hh66dw <hh66dw@163.com>
License: MIT License
Project-URL: Homepage, https://gitee.com/hh66dw/brief_develop
Project-URL: Documentation, https://gitee.com/hh66dw/brief_develop#readme
Project-URL: Repository, https://gitee.com/hh66dw/brief_develop
Project-URL: Issues, https://gitee.com/hh66dw/brief_develop/issues
Classifier: Development Status :: 4 - Beta
Classifier: Intended Audience :: Developers
Classifier: License :: OSI Approved :: MIT License
Classifier: Programming Language :: Python :: 3
Classifier: Programming Language :: Python :: 3.7
Classifier: Programming Language :: Python :: 3.8
Classifier: Programming Language :: Python :: 3.9
Classifier: Programming Language :: Python :: 3.10
Classifier: Programming Language :: Python :: 3.11
Classifier: Topic :: Software Development :: Libraries :: Python Modules
Requires-Python: >=3.7
License-File: LICENSE
Requires-Dist: termcolor==2.4.0
Provides-Extra: dev
Requires-Dist: pytest>=6.0; extra == "dev"
Requires-Dist: pytest-cov>=2.0; extra == "dev"
Requires-Dist: black>=22.0; extra == "dev"
Requires-Dist: flake8>=4.0; extra == "dev"
Requires-Dist: isort>=5.0; extra == "dev"
Dynamic: license-file
